link_nlp/__init__.py
link_nlp/data/ca_synth_mc.csv
link_nlp/data/codice_appalti_allegati.csv
link_nlp/data/codice_appalti_correttivo.csv
link_nlp/data/codice_appalti_qa.jsonl
link_nlp/data/data_appalti_v5.csv
link_nlp/data/generated_output_mc.jsonl
link_nlp/data/generation_with_correttivo.csv
link_nlp/data/generazione_contesti_correttivi_v4.csv
link_nlp/data/generazione_contesti_v4.csv
link_nlp/data/generazione_v1.csv
link_nlp/data/generazione_v2.csv
link_nlp/data/legal_genie_cod_app.jsonl
link_nlp/data/references_appalti.jsonl
link_nlp/data/synth_qa_claude_3_5_sonnet_20241022.jsonl
link_nlp/data/synth_qa_correttivo_topics.jsonl
link_nlp/data/synth_qa_gpt_4o.jsonl
link_nlp/data_acquisition/BrowserSessionClass.py
link_nlp/data_acquisition/DownloadReferencesFromCsv.py
link_nlp/data_acquisition/__init__.py
link_nlp/data_acquisition/normattiva.py
link_nlp/data_acquisition/normattivaFunctions.py
link_nlp/database/MilvusDbAlternative.py
link_nlp/database/__init__.py
link_nlp/database/milvusDb.py
link_nlp/main/__init__.py
link_nlp/main/main.py
link_nlp/main/run.py
link_nlp/retrieval/ContextualRetrieval.py
link_nlp/retrieval/ContextualRetrievalAlternative.py
link_nlp/retrieval/NewContextRetrieval.py
link_nlp/retrieval/__init__.py
link_nlp/testing/CalcoloMetriche.py
link_nlp/testing/TestingFunction.py
link_nlp/testing/__init__.py
link_nlp/text_processing/__init__.py
link_nlp/text_processing/context_generation.py
link_nlp/text_processing/findReferencesOptimized.py
link_nlp/text_processing/generationUtils.py
link_nlp/text_processing/ner_extractor.py
link_nlp/text_processing/text_generation.py
link_nlp/text_processing/text_generation_alt.py
link_nlp/text_processing/text_generation_unified.py
link_nlp-0.4.5.dist-info/METADATA
link_nlp-0.4.5.dist-info/WHEEL
link_nlp-0.4.5.dist-info/entry_points.txt
link_nlp-0.4.5.dist-info/top_level.txt
link_nlp-0.4.5.dist-info/RECORD
