Metadata-Version: 2.4
Name: link-nlp
Version: 0.4.5
Summary: Legal Information Knowledge with Natural Language Processing
Home-page: https://github.com/LorMolf/link
Author: Lorenzo Molfetta
Author-email: lorenzo.molfetta@unibo.it
Classifier: Development Status :: 3 - Alpha
Classifier: Intended Audience :: Legal Industry
Classifier: License :: OSI Approved :: MIT License
Classifier: Programming Language :: Python :: 3
Classifier: Programming Language :: Python :: 3.8
Classifier: Programming Language :: Python :: 3.9
Classifier: Programming Language :: Python :: 3.10
Requires-Python: >=3.8
Requires-Dist: transformers>=4.0.0
Requires-Dist: torch>=2.0.0
Requires-Dist: numpy>=1.20.0
Requires-Dist: pandas>=1.3.0
Requires-Dist: requests>=2.25.0
Requires-Dist: beautifulsoup4>=4.9.0
Requires-Dist: selenium>=4.0.0
Requires-Dist: pymilvus>=2.0.0
Requires-Dist: vllm>=0.1.0
Requires-Dist: spacy>=3.0.0
Requires-Dist: tqdm>=4.62.0
Requires-Dist: accelerate>=0.20.0
Requires-Dist: cymem>=2.0.0
Requires-Dist: preshed>=3.0.0
Requires-Dist: murmurhash>=1.0.0
Requires-Dist: thinc>=8.0.0
Requires-Dist: ninja>=1.10.0
Requires-Dist: packaging>=21.0
Requires-Dist: psutil>=5.8.0
Requires-Dist: ray>=2.0.0
Requires-Dist: protobuf>=3.20.0
Requires-Dist: sentencepiece>=0.1.99
Provides-Extra: gliner
Requires-Dist: gliner>=0.1.0; extra == "gliner"
Provides-Extra: transformers
Requires-Dist: transformers>=4.0.0; extra == "transformers"
Requires-Dist: torch>=2.0.0; extra == "transformers"
Requires-Dist: accelerate>=0.20.0; extra == "transformers"
Dynamic: author
Dynamic: author-email
Dynamic: classifier
Dynamic: description
Dynamic: description-content-type
Dynamic: home-page
Dynamic: provides-extra
Dynamic: requires-dist
Dynamic: requires-python
Dynamic: summary
